pybioinformatic/__init__.py
pybioinformatic/bed.py
pybioinformatic/biomatplotlib.py
pybioinformatic/biomysql.py
pybioinformatic/biopandas.py
pybioinformatic/blast.py
pybioinformatic/decompressing_file.py
pybioinformatic/fasta.py
pybioinformatic/fastq.py
pybioinformatic/font/Arial.ttf
pybioinformatic/genotype.py
pybioinformatic/gff.py
pybioinformatic/gtf.py
pybioinformatic/NGS/__init__.py
pybioinformatic/NGS/base.py
pybioinformatic/NGS/DNA_seq.py
pybioinformatic/NGS/RNA_seq.py
pybioinformatic/sequence.py
pybioinformatic/show_info.py
pybioinformatic/task_manager.py
pybioinformatic/timer.py
pybioinformatic/util.py
pybioinformatic/vcf.py
pybioinformatic-1.2.5.dist-info/LICENCE
pybioinformatic-1.2.5.dist-info/METADATA
pybioinformatic-1.2.5.dist-info/WHEEL
pybioinformatic-1.2.5.dist-info/RECORD
