Metadata-Version: 2.1
Name: pybioinformatic
Version: 1.2.5
Summary: Bioinformatic python package.
Home-page: https://github.com/wenlinXu-njfu/Leo
License: MIT
Author: Wenlin Xu
Author-email: wenlinxu.njfu@outlook.com
Requires-Python: >=3.8
Classifier: License :: OSI Approved :: MIT License
Classifier: Programming Language :: Python :: 3
Classifier: Programming Language :: Python :: 3.8
Classifier: Programming Language :: Python :: 3.9
Classifier: Programming Language :: Python :: 3.10
Classifier: Programming Language :: Python :: 3.11
Classifier: Programming Language :: Python :: 3.12
Classifier: Programming Language :: Python :: 3.13
Requires-Dist: ViennaRNA (>=2.6.4)
Requires-Dist: click (>=8.1.7)
Requires-Dist: matplotlib (>=3.7.5)
Requires-Dist: natsort (>=8.4.0)
Requires-Dist: openpyxl (>=3.1.2)
Requires-Dist: pandas (>=2.0.3)
Requires-Dist: pymysql (>=1.1.1)
Requires-Dist: ray (>=2.10.0)
Requires-Dist: seaborn (>=0.13.2)
Requires-Dist: sshtunnel (>=0.4.0)
Requires-Dist: statsmodels (>=0.14.1)
Requires-Dist: swifter (>=1.4.0)
Requires-Dist: tqdm (>=4.66.2)
Requires-Dist: typing_extensions (>=4.9.0)
Requires-Dist: xlrd (>=2.0.1)
Requires-Dist: xlsxwriter (>=3.2.0)
Requires-Dist: xlwt (>=1.3.0)
